assume/__init__.py
assume/world.py
assume/common/__init__.py
assume/common/base.py
assume/common/exceptions.py
assume/common/fast_pandas.py
assume/common/forecast_initialisation.py
assume/common/forecaster.py
assume/common/grid_utils.py
assume/common/mango_serializer.py
assume/common/market_objects.py
assume/common/outputs.py
assume/common/units_operator.py
assume/common/utils.py
assume/markets/__init__.py
assume/markets/base_market.py
assume/markets/clearing_algorithms/__init__.py
assume/markets/clearing_algorithms/complex_clearing.py
assume/markets/clearing_algorithms/complex_clearing_dmas.py
assume/markets/clearing_algorithms/contracts.py
assume/markets/clearing_algorithms/nodal_clearing.py
assume/markets/clearing_algorithms/redispatch.py
assume/markets/clearing_algorithms/simple.py
assume/reinforcement_learning/__init__.py
assume/reinforcement_learning/buffer.py
assume/reinforcement_learning/learning_role.py
assume/reinforcement_learning/learning_utils.py
assume/reinforcement_learning/neural_network_architecture.py
assume/reinforcement_learning/tensorboard_logger.py
assume/reinforcement_learning/algorithms/__init__.py
assume/reinforcement_learning/algorithms/base_algorithm.py
assume/reinforcement_learning/algorithms/matd3.py
assume/scenario/loader_amiris.py
assume/scenario/loader_csv.py
assume/scenario/loader_oeds.py
assume/scenario/loader_pypsa.py
assume/scenario/oeds/infrastructure.py
assume/scenario/oeds/static.py
assume/strategies/__init__.py
assume/strategies/advanced_orders.py
assume/strategies/dmas_powerplant.py
assume/strategies/dmas_storage.py
assume/strategies/extended.py
assume/strategies/flexable.py
assume/strategies/flexable_storage.py
assume/strategies/interactive_strategies.py
assume/strategies/learning_strategies.py
assume/strategies/naive_strategies.py
assume/strategies/portfolio_strategies.py
assume/units/__init__.py
assume/units/building.py
assume/units/demand.py
assume/units/dsm_load_shift.py
assume/units/dst_components.py
assume_framework-0.5.6.dist-info/licenses/LICENSE.txt
assume_framework-0.5.6.dist-info/METADATA
assume_framework-0.5.6.dist-info/WHEEL
assume_framework-0.5.6.dist-info/entry_points.txt
assume_framework-0.5.6.dist-info/top_level.txt
assume_framework-0.5.6.dist-info/RECORD
