Metadata-Version: 2.4
Name: assume-framework
Version: 0.5.6
Summary: ASSUME - Agent-Based Electricity Markets Simulation Toolbox
Author-email: ASSUME Developers <contact@assume-project.de>
License-Expression: AGPL-3.0-or-later
Project-URL: Homepage, https://assume-project.de/
Project-URL: Repository, https://github.com/assume-framework/assume
Project-URL: Documentation, https://assume.readthedocs.io
Project-URL: Issues, https://github.com/assume-framework/assume/issues
Project-URL: Changelog, https://assume.readthedocs.io/en/latest/release_notes.html
Keywords: agent based simulation,energy market,reinforcement learning,market simulation,simulation
Classifier: Development Status :: 4 - Beta
Classifier: Intended Audience :: Developers
Classifier: Operating System :: OS Independent
Classifier: Framework :: AsyncIO
Classifier: Topic :: Scientific/Engineering
Classifier: Topic :: Software Development :: Libraries :: Python Modules
Classifier: Programming Language :: Python :: 3 :: Only
Classifier: Programming Language :: Python :: 3.10
Classifier: Programming Language :: Python :: 3.11
Classifier: Programming Language :: Python :: 3.12
Classifier: Programming Language :: Python :: 3.13
Requires-Python: >=3.10
License-File: LICENSE.txt
Requires-Dist: argcomplete>=3.1.4
Requires-Dist: nest-asyncio>=1.5.6
Requires-Dist: mango-agents>=2.1.3
Requires-Dist: numpy>=1.26.4
Requires-Dist: tqdm>=4.64.1
Requires-Dist: python-dateutil>=2.8.2
Requires-Dist: sqlalchemy>=2.0.9
Requires-Dist: pandas>=2.0.0
Requires-Dist: psycopg2-binary>=2.9.5
Requires-Dist: pyyaml>=6.0
Requires-Dist: pyyaml-include>=2.2a
Requires-Dist: pyomo>=6.8.0
Requires-Dist: xarray
Requires-Dist: highspy
Provides-Extra: learning
Requires-Dist: torch>=2.0.1; extra == "learning"
Requires-Dist: tensorboard>=2.7.0; extra == "learning"
Provides-Extra: network
Requires-Dist: pypsa; extra == "network"
Provides-Extra: oeds
Requires-Dist: demandlib>=0.1.9; extra == "oeds"
Requires-Dist: holidays<1.0; extra == "oeds"
Requires-Dist: pvlib>=0.10.2; extra == "oeds"
Requires-Dist: windpowerlib>=0.2.1; extra == "oeds"
Provides-Extra: test
Requires-Dist: ruff>=0.14.6; extra == "test"
Requires-Dist: mypy>=1.1.1; extra == "test"
Requires-Dist: matplotlib>=3.7.2; extra == "test"
Requires-Dist: pytest>=9; extra == "test"
Requires-Dist: pytest-cov>=7.0.0; extra == "test"
Requires-Dist: pytest-asyncio>=1.3.0; extra == "test"
Provides-Extra: all
Requires-Dist: assume-framework[learning,network,oeds]; extra == "all"
Provides-Extra: docs
Requires-Dist: sphinx<9; extra == "docs"
Requires-Dist: sphinx-book-theme>=1.1.4; extra == "docs"
Requires-Dist: nbsphinx>=0.9.7; extra == "docs"
Requires-Dist: nbsphinx-link>=1.3.1; extra == "docs"
Requires-Dist: sphinx-argparse>=0.5.2; extra == "docs"
Requires-Dist: sphinxcontrib-mermaid>=1.0.0; extra == "docs"
Dynamic: license-file
